Cyrcos/Cyrcos.py
Cyrcos/__init__.py
Cyrcos-1.0.dist-info/DESCRIPTION.rst
Cyrcos-1.0.dist-info/METADATA
Cyrcos-1.0.dist-info/RECORD
Cyrcos-1.0.dist-info/WHEEL
Cyrcos-1.0.dist-info/metadata.json
Cyrcos-1.0.dist-info/top_level.txt
